biblib/__init__.py
biblib/_bibdb.py
biblib/_btfile.py
biblib/_entry.py
biblib/_reader.py
biblib/_writer.py
biblib/dev/__init__.py
biblib/dev/_doilib.py
biblib/dev/_isbnlib.py
biblib/dev/_latexenc.py
biblib/dev/_parser.py
biblib-0.1.dev4.dist-info/DESCRIPTION.rst
biblib-0.1.dev4.dist-info/METADATA
biblib-0.1.dev4.dist-info/RECORD
biblib-0.1.dev4.dist-info/WHEEL
biblib-0.1.dev4.dist-info/metadata.json
biblib-0.1.dev4.dist-info/top_level.txt
