Metadata-Version: 2.0
Name: biblib
Version: 0.1.dev4
Summary: A library to handle BibTeX bibliographic data.
Home-page: http://pythonhosted.org/biblib
Author: Frank Roemer
Author-email: froemer76@googlemail.com
License: MIT
Keywords: BibTeX ISBN DOI citation
Platform: UNKNOWN
Classifier: Operating System :: OS Independent
Classifier: Development Status :: 2 - Pre-Alpha
Classifier: License :: OSI Approved :: MIT License
Classifier: Intended Audience :: Developers
Classifier: Topic :: Text Processing :: General
Classifier: Topic :: Text Processing :: Markup :: LaTeX
Classifier: Topic :: Software Development :: Libraries :: Python Modules
Classifier: Programming Language :: Python :: 2.7
Classifier: Programming Language :: Python :: 2 :: Only
Requires-Dist: isbnlib (>=3.5.6)
Requires-Dist: python-magic (>=0.4.10)
